pysftp-stubs/METADATA.toml
pysftp-stubs/__init__.pyi
pysftp-stubs/exceptions.pyi
pysftp-stubs/helpers.pyi
pysftp-stubs/py.typed
types_pysftp-0.2.17.20241117.dist-info/METADATA
types_pysftp-0.2.17.20241117.dist-info/WHEEL
types_pysftp-0.2.17.20241117.dist-info/top_level.txt
types_pysftp-0.2.17.20241117.dist-info/RECORD
