Metadata-Version: 2.1
Name: types-pysftp
Version: 0.2.17.20241117
Summary: Typing stubs for pysftp
Home-page: https://github.com/python/typeshed
License: Apache-2.0
Project-URL: GitHub, https://github.com/python/typeshed
Project-URL: Changes, https://github.com/typeshed-internal/stub_uploader/blob/main/data/changelogs/pysftp.md
Project-URL: Issue tracker, https://github.com/python/typeshed/issues
Project-URL: Chat, https://gitter.im/python/typing
Classifier: License :: OSI Approved :: Apache Software License
Classifier: Programming Language :: Python :: 3
Classifier: Typing :: Stubs Only
Requires-Python: >=3.8
Requires-Dist: types-paramiko
